LICENSE
MANIFEST.in
README.rst
setup.py
authorize/__init__.py
authorize/models.py
authorize/urls.py
authorize/views.py
authorize/api/__init__.py
authorize/api/serializers.py
authorize/api/urls.py
authorize/api/views.py
authorize/migrations/0001_initial.py
authorize/migrations/__init__.py
django_authorize.egg-info/PKG-INFO
django_authorize.egg-info/SOURCES.txt
django_authorize.egg-info/dependency_links.txt
django_authorize.egg-info/requires.txt
django_authorize.egg-info/top_level.txt
docs/api/menu-api.md
tests/__init__.py
tests/test_menu.py